enverge_proxy/__init__.py
enverge_proxy/main.py
enverge_proxy-0.1.2.dist-info/licenses/LICENSE
enverge_proxy-0.1.2.dist-info/METADATA
enverge_proxy-0.1.2.dist-info/WHEEL
enverge_proxy-0.1.2.dist-info/entry_points.txt
enverge_proxy-0.1.2.dist-info/top_level.txt
enverge_proxy-0.1.2.dist-info/RECORD
