Metadata-Version: 2.4
Name: enverge_proxy
Version: 0.1.2
Summary: A proxy server for Enverge workspaces
Author-email: "Enverge.ai" <tudor@enverge.ai>
Project-URL: Homepage, https://github.com/enverge-ai/enverge-proxy
Classifier: Programming Language :: Python :: 3
Classifier: License :: OSI Approved :: MIT License
Classifier: Operating System :: OS Independent
Requires-Python: >=3.10
License-File: LICENSE
Requires-Dist: click
Provides-Extra: dev
Requires-Dist: black; extra == "dev"
Requires-Dist: isort; extra == "dev"
Dynamic: license-file
